[
  {
    "Kunnskapsgrunnlag - Grunntypeinndelingen": "2",
    "HTK": "M1",
    "Navn": "Eufotisk fast saltvannsbunn",
    "PrK": "1",
    "PrK-tekst": "Uten variasjon i artssammensetning betinget av strukturerende artsgruppe",
    "GrL": "0",
    "Definisjonsgrunnlag-tekst": "normal hovedtype",
    "NiN[1] ": "M11 [1-5, pp]",
    "dLKM": "",
    "hLKM": "VF,DL,SA",
    "tLKM": "HF,S1,IF",
    "uLKM": "VR,RU ",
    "Kunnskapsgrunnlag - Hovedtypen generelt": "3"
  },
  {
    "Kunnskapsgrunnlag - Grunntypeinndelingen": "2",
    "HTK": "M2",
    "Navn": "Afotisk fast saltvannsbunn",
    "PrK": "1",
    "PrK-tekst": "Uten variasjon i artssammensetning betinget av strukturerende artsgruppe",
    "GrL": "0",
    "Definisjonsgrunnlag-tekst": "normal hovedtype",
    "NiN[1] ": "M8 [1]",
    "dLKM": "",
    "hLKM": "DM,VF",
    "tLKM": "HF,BK",
    "uLKM": "SA,S1,RU",
    "Kunnskapsgrunnlag - Hovedtypen generelt": "1"
  },
  {
    "Kunnskapsgrunnlag - Grunntypeinndelingen": "3",
    "HTK": "M3",
    "Navn": "Fast fjærebeltebunn",
    "PrK": "1",
    "PrK-tekst": "Uten variasjon i artssammensetning betinget av strukturerende artsgruppe",
    "GrL": "0",
    "Definisjonsgrunnlag-tekst": "normal hovedtype",
    "NiN[1] ": "S4",
    "dLKM": "",
    "hLKM": "VF,TV,SA ",
    "tLKM": "HF,IF ",
    "uLKM": "S1,VR,RU",
    "Kunnskapsgrunnlag - Hovedtypen generelt": "3"
  },
  {
    "Kunnskapsgrunnlag - Grunntypeinndelingen": "2",
    "HTK": "M4",
    "Navn": "Eufotisk marin sedimentbunn",
    "PrK": "1",
    "PrK-tekst": "Uten variasjon i artssammensetning betinget av strukturerende artsgruppe",
    "GrL": "0",
    "Definisjonsgrunnlag-tekst": "normal hovedtype",
    "NiN[1] ": "M4 pp., M13, M15",
    "dLKM": "",
    "hLKM": "S3 ",
    "tLKM": "DL,SA,IO,KA,SE ",
    "uLKM": "",
    "Kunnskapsgrunnlag - Hovedtypen generelt": "2"
  },
  {
    "Kunnskapsgrunnlag - Grunntypeinndelingen": "2",
    "HTK": "M5",
    "Navn": "Afotisk marin sedimentbunn",
    "PrK": "1",
    "PrK-tekst": "Uten variasjon i artssammensetning betinget av strukturerende artsgruppe",
    "GrL": "0",
    "Definisjonsgrunnlag-tekst": "normal hovedtype",
    "NiN[1] ": "M4 pp, M12, M14 [1]",
    "dLKM": "",
    "hLKM": "S3,DM ",
    "tLKM": "IO ",
    "uLKM": "VF",
    "Kunnskapsgrunnlag - Hovedtypen generelt": "2"
  },
  {
    "Kunnskapsgrunnlag - Grunntypeinndelingen": "3",
    "HTK": "M6",
    "Navn": "Korallrev-bunn",
    "PrK": "2",
    "PrK-tekst": "Med variasjon i artssammensetning betinget av strukturerende artsgruppe",
    "GrL": "A",
    "Definisjonsgrunnlag-tekst": "normal, strukturerende artsgruppe",
    "NiN[1] ": "M6",
    "dLKM": "",
    "hLKM": "",
    "tLKM": "DM ",
    "uLKM": "LK",
    "Kunnskapsgrunnlag - Hovedtypen generelt": "4"
  },
  {
    "Kunnskapsgrunnlag - Grunntypeinndelingen": "3",
    "HTK": "M7",
    "Navn": "Marin undervannseng",
    "PrK": "2",
    "PrK-tekst": "Med variasjon i artssammensetning betinget av strukturerende artsgruppe",
    "GrL": "A",
    "Definisjonsgrunnlag-tekst": "normal, strukturerende artsgruppe",
    "NiN[1] ": "M15 [3]",
    "dLKM": "",
    "hLKM": "",
    "tLKM": "SA,TV ",
    "uLKM": "S3",
    "Kunnskapsgrunnlag - Hovedtypen generelt": "4"
  },
  {
    "Kunnskapsgrunnlag - Grunntypeinndelingen": "2",
    "HTK": "M8",
    "Navn": "Helofytt-saltvannsump",
    "PrK": "2",
    "PrK-tekst": "Med variasjon i artssammensetning betinget av strukturerende artsgruppe",
    "GrL": "A ",
    "Definisjonsgrunnlag-tekst": "normal, strukturerende artsgruppe",
    "NiN[1] ": "S7 [10, 12]",
    "dLKM": "",
    "hLKM": "",
    "tLKM": "",
    "uLKM": "SA,IO,TV ",
    "Kunnskapsgrunnlag - Hovedtypen generelt": "2"
  },
  {
    "Kunnskapsgrunnlag - Grunntypeinndelingen": "2",
    "HTK": "M9",
    "Navn": "Littoralbasseng-bunn",
    "PrK": "3",
    "PrK-tekst": "Preget av miljøstress",
    "GrL": "S",
    "Definisjonsgrunnlag-tekst": "miljøstressbetinget",
    "NiN[1] ": "M11 [6,7]",
    "dLKM": "SM ",
    "hLKM": "SM,TV ",
    "tLKM": "SE",
    "uLKM": "",
    "Kunnskapsgrunnlag - Hovedtypen generelt": "2"
  },
  {
    "Kunnskapsgrunnlag - Grunntypeinndelingen": "2",
    "HTK": "M10",
    "Navn": "Marin grotte og overheng",
    "PrK": "3",
    "PrK-tekst": "Preget av miljøstress",
    "GrL": "S",
    "Definisjonsgrunnlag-tekst": "miljøstressbetinget",
    "NiN[1] ": "M8 [2] pp. M11 [5] pp.",
    "dLKM": "GS",
    "hLKM": "DL ",
    "tLKM": "GS ",
    "uLKM": "",
    "Kunnskapsgrunnlag - Hovedtypen generelt": "1"
  },
  {
    "Kunnskapsgrunnlag - Grunntypeinndelingen": "1",
    "HTK": "M11",
    "Navn": "Kaldt gassoppkomme",
    "PrK": "3",
    "PrK-tekst": "Preget av miljøstress",
    "GrL": "S",
    "Definisjonsgrunnlag-tekst": "miljøstressbetinget",
    "NiN[1] ": "M2",
    "dLKM": "KI",
    "hLKM": "DM ",
    "tLKM": "KI,KT ",
    "uLKM": "",
    "Kunnskapsgrunnlag - Hovedtypen generelt": "1"
  },
  {
    "Kunnskapsgrunnlag - Grunntypeinndelingen": "1",
    "HTK": "M12",
    "Navn": "Varm havkilde",
    "PrK": "3",
    "PrK-tekst": "Preget av miljøstress",
    "GrL": "S ",
    "Definisjonsgrunnlag-tekst": "miljøstressbetinget",
    "NiN[1] ": "M3",
    "dLKM": "KI,JV ",
    "hLKM": "JV,DM",
    "tLKM": "",
    "uLKM": "",
    "Kunnskapsgrunnlag - Hovedtypen generelt": "1"
  },
  {
    "Kunnskapsgrunnlag - Grunntypeinndelingen": "3",
    "HTK": "M13",
    "Navn": "Marin sedimentbunn preget av oksygenmangel",
    "PrK": "3",
    "PrK-tekst": "Preget av miljøstress",
    "GrL": "S",
    "Definisjonsgrunnlag-tekst": "miljøstressbetinget",
    "NiN[1] ": "M5 [1] M14[2]",
    "dLKM": "OM",
    "hLKM": "",
    "tLKM": "OM,DL",
    "uLKM": "",
    "Kunnskapsgrunnlag - Hovedtypen generelt": "2"
  },
  {
    "Kunnskapsgrunnlag - Grunntypeinndelingen": "1",
    "HTK": "M14",
    "Navn": "Sterkt endret eller ny fast saltvannsbunn",
    "PrK": "12a",
    "PrK-tekst": "Sterkt endret system uten eller med svake spor etter av hevd - Rask suksesjon",
    "GrL": "N",
    "Definisjonsgrunnlag-tekst": "sterk menneskebetinget forstyrrelse",
    "NiN[1] ": "M1 pp. S1 [3,4]",
    "dLKM": "SX",
    "hLKM": "DL ",
    "tLKM": "",
    "uLKM": "VF,SA",
    "Kunnskapsgrunnlag - Hovedtypen generelt": "1"
  },
  {
    "Kunnskapsgrunnlag - Grunntypeinndelingen": "1",
    "HTK": "M15",
    "Navn": "Sterkt endret eller ny marin sedimentbunn ",
    "PrK": "12a",
    "PrK-tekst": "Sterkt endret system uten eller med svake spor etter av hevd - Rask suksesjon",
    "GrL": "N",
    "Definisjonsgrunnlag-tekst": "sterk menneskebetinget forstyrrelse",
    "NiN[1] ": "M1 pp. S1 [1,2]",
    "dLKM": "SX",
    "hLKM": "",
    "tLKM": "S3,HS",
    "uLKM": "DL,SA",
    "Kunnskapsgrunnlag - Hovedtypen generelt": "2"
  },
  {
    "Kunnskapsgrunnlag - Grunntypeinndelingen": "2",
    "HTK": "L1",
    "Navn": "Eufotisk fast ferskvannsbunn ",
    "PrK": "1",
    "PrK-tekst": "Uten variasjon i artssammensetning betinget av strukturerende artsgruppe",
    "GrL": "0",
    "Definisjonsgrunnlag-tekst": "normal hovedtype",
    "NiN[1] ": "F6",
    "dLKM": "",
    "hLKM": "KA ",
    "tLKM": "VF,HU ",
    "uLKM": "DL,IF",
    "Kunnskapsgrunnlag - Hovedtypen generelt": "3"
  },
  {
    "Kunnskapsgrunnlag - Grunntypeinndelingen": "2",
    "HTK": "L2",
    "Navn": "Eufotisk limnisk sedimentbunn",
    "PrK": "1",
    "PrK-tekst": "Uten variasjon i artssammensetning betinget av strukturerende artsgruppe",
    "GrL": "0",
    "Definisjonsgrunnlag-tekst": "normal hovedtype",
    "NiN[1] ": "F5 F7[1, 3,4]",
    "dLKM": "",
    "hLKM": "S3,KA ",
    "tLKM": "IO,VT,SE ",
    "uLKM": "VF,HU,DL,IF",
    "Kunnskapsgrunnlag - Hovedtypen generelt": "3"
  },
  {
    "Kunnskapsgrunnlag - Grunntypeinndelingen": "1",
    "HTK": "L3",
    "Navn": "Afotisk limnisk sedimentbunn",
    "PrK": "1",
    "PrK-tekst": "Uten variasjon i artssammensetning betinget av strukturerende artsgruppe",
    "GrL": "0",
    "Definisjonsgrunnlag-tekst": "normal hovedtype",
    "NiN[1] ": "F4",
    "dLKM": "",
    "hLKM": "",
    "tLKM": "KA ",
    "uLKM": "IO",
    "Kunnskapsgrunnlag - Hovedtypen generelt": "2"
  },
  {
    "Kunnskapsgrunnlag - Grunntypeinndelingen": "3",
    "HTK": "L4",
    "Navn": "Helofytt-ferskvannssump",
    "PrK": "2",
    "PrK-tekst": "Med variasjon i artssammensetning betinget av strukturerende artsgruppe",
    "GrL": "A",
    "Definisjonsgrunnlag-tekst": "normal, strukturerende artsgruppe",
    "NiN[1] ": "F7 [5, 6]",
    "dLKM": "",
    "hLKM": "",
    "tLKM": "KA ",
    "uLKM": "S3,IO,IF",
    "Kunnskapsgrunnlag - Hovedtypen generelt": "4"
  },
  {
    "Kunnskapsgrunnlag - Grunntypeinndelingen": "1",
    "HTK": "L5",
    "Navn": "Ferskvannskildebunn",
    "PrK": "3",
    "PrK-tekst": "Preget av miljøstress",
    "GrL": "S ",
    "Definisjonsgrunnlag-tekst": "miljøstressbetinget",
    "NiN[1] ": "F2",
    "dLKM": "KI",
    "hLKM": "",
    "tLKM": "KT,KA ",
    "uLKM": "S3,VF",
    "Kunnskapsgrunnlag - Hovedtypen generelt": "2"
  },
  {
    "Kunnskapsgrunnlag - Grunntypeinndelingen": "2",
    "HTK": "L6",
    "Navn": "Afotisk limnisk sedimentbunn preget av oksygenmangel",
    "PrK": "3",
    "PrK-tekst": "Preget av miljøstress",
    "GrL": "S",
    "Definisjonsgrunnlag-tekst": "miljøstressbetinget",
    "NiN[1] ": "F3",
    "dLKM": "OM",
    "hLKM": "",
    "tLKM": "OM ",
    "uLKM": "KA",
    "Kunnskapsgrunnlag - Hovedtypen generelt": "3"
  },
  {
    "Kunnskapsgrunnlag - Grunntypeinndelingen": "1",
    "HTK": "L7",
    "Navn": "Sterkt endret eller ny fast ferskvannsbunn",
    "PrK": "12a",
    "PrK-tekst": "Sterkt endret system uten eller med svake spor etter av hevd - Rask suksesjon",
    "GrL": "N",
    "Definisjonsgrunnlag-tekst": "sterk menneskebetinget forstyrrelse",
    "NiN[1] ": "F1 p.p.",
    "dLKM": "SX",
    "hLKM": "",
    "tLKM": "HS",
    "uLKM": "DL",
    "Kunnskapsgrunnlag - Hovedtypen generelt": "1"
  },
  {
    "Kunnskapsgrunnlag - Grunntypeinndelingen": "1",
    "HTK": "L8",
    "Navn": "Sterkt endret eller ny limnisk sedimentbunn",
    "PrK": "12a",
    "PrK-tekst": "Sterkt endret system uten eller med svake spor etter av hevd - Rask suksesjon",
    "GrL": "N",
    "Definisjonsgrunnlag-tekst": "sterk menneskebetinget forstyrrelse",
    "NiN[1] ": "F1 p.p.",
    "dLKM": "SX",
    "hLKM": "",
    "tLKM": "HS",
    "uLKM": "DL",
    "Kunnskapsgrunnlag - Hovedtypen generelt": "2"
  },
  {
    "Kunnskapsgrunnlag - Grunntypeinndelingen": "2",
    "HTK": "T1",
    "Navn": "Nakent berg",
    "PrK": "1",
    "PrK-tekst": "Uten variasjon i artssammensetning betinget av strukturerende artsgruppe",
    "GrL": "0L",
    "Definisjonsgrunnlag-tekst": "normal, ikke jorddekt",
    "NiN[1] ": "T9, T14, T20",
    "dLKM": "",
    "hLKM": "KA,UE,OR ",
    "tLKM": "HF,VF,VS,LA,NG,VI,SV ",
    "uLKM": "IF,BK",
    "Kunnskapsgrunnlag - Hovedtypen generelt": "3"
  },
  {
    "Kunnskapsgrunnlag - Grunntypeinndelingen": "3",
    "HTK": "T2",
    "Navn": "Åpen grunnlendt mark ",
    "PrK": "1",
    "PrK-tekst": "Uten variasjon i artssammensetning betinget av strukturerende artsgruppe",
    "GrL": "0",
    "Definisjonsgrunnlag-tekst": "normal hovedtype",
    "NiN[1] ": "T25",
    "dLKM": "",
    "hLKM": "KA ",
    "tLKM": "UF ",
    "uLKM": "VM,BK,HI",
    "Kunnskapsgrunnlag - Hovedtypen generelt": "2"
  },
  {
    "Kunnskapsgrunnlag - Grunntypeinndelingen": "4",
    "HTK": "T3",
    "Navn": "Fjellhei, leside og tundra",
    "PrK": "1",
    "PrK-tekst": "Uten variasjon i artssammensetning betinget av strukturerende artsgruppe",
    "GrL": "0",
    "Definisjonsgrunnlag-tekst": "normal hovedtype",
    "NiN[1] ": "T29 [1-16]",
    "dLKM": "",
    "hLKM": "KA,UF ",
    "tLKM": "KI ",
    "uLKM": "BK,HI,RU,VM",
    "Kunnskapsgrunnlag - Hovedtypen generelt": "4"
  },
  {
    "Kunnskapsgrunnlag - Grunntypeinndelingen": "3",
    "HTK": "T4",
    "Navn": "Fastmarksskogsmark",
    "PrK": "2",
    "PrK-tekst": "Med variasjon i artssammensetning betinget av strukturerende artsgruppe",
    "GrL": "A",
    "Definisjonsgrunnlag-tekst": "normal, strukturerende artsgruppe",
    "NiN[1] ": "T23",
    "dLKM": "",
    "hLKM": "UF,KA ",
    "tLKM": "KI ",
    "uLKM": "BK,HI,SU,RU,SS,S1,VM,VS,UE",
    "Kunnskapsgrunnlag - Hovedtypen generelt": "4"
  },
  {
    "Kunnskapsgrunnlag - Grunntypeinndelingen": "2",
    "HTK": "T5",
    "Navn": "Grotte og overheng",
    "PrK": "3",
    "PrK-tekst": "Preget av miljøstress",
    "GrL": "SL ",
    "Definisjonsgrunnlag-tekst": "miljøstressbetinget, ikke jorddekt",
    "NiN[1] ": "T19 T20 pp.",
    "dLKM": "GS",
    "hLKM": "GS,KA ",
    "tLKM": "UE ",
    "uLKM": "BK,LA",
    "Kunnskapsgrunnlag - Hovedtypen generelt": "1"
  },
  {
    "Kunnskapsgrunnlag - Grunntypeinndelingen": "2",
    "HTK": "T6",
    "Navn": "Strandberg",
    "PrK": "3",
    "PrK-tekst": "Preget av miljøstress",
    "GrL": "SL ",
    "Definisjonsgrunnlag-tekst": "miljøstressbetinget, ikke jorddekt",
    "NiN[1] ": "S5",
    "dLKM": "TV,SA ",
    "hLKM": "TV ",
    "tLKM": "KA,VF,HF,IF",
    "uLKM": "",
    "Kunnskapsgrunnlag - Hovedtypen generelt": "3"
  },
  {
    "Kunnskapsgrunnlag - Grunntypeinndelingen": "4",
    "HTK": "T7",
    "Navn": "Snøleie",
    "PrK": "3",
    "PrK-tekst": "Preget av miljøstress",
    "GrL": "S",
    "Definisjonsgrunnlag-tekst": "miljøstressbetinget",
    "NiN[1] ": "T30 pp.",
    "dLKM": "SV ",
    "hLKM": "KA,SV ",
    "tLKM": "KI ",
    "uLKM": "VM,HI,S1",
    "Kunnskapsgrunnlag - Hovedtypen generelt": "4"
  },
  {
    "Kunnskapsgrunnlag - Grunntypeinndelingen": "3",
    "HTK": "T8",
    "Navn": "Fuglefjell-eng og fugletopp",
    "PrK": "3",
    "PrK-tekst": "Preget av miljøstress",
    "GrL": "S",
    "Definisjonsgrunnlag-tekst": "miljøstressbetinget",
    "NiN[1] ": "T15",
    "dLKM": "NG",
    "hLKM": "NG ",
    "tLKM": "KI,UF ",
    "uLKM": "KA,HI ",
    "Kunnskapsgrunnlag - Hovedtypen generelt": "3"
  },
  {
    "Kunnskapsgrunnlag - Grunntypeinndelingen": "1",
    "HTK": "T9",
    "Navn": "Mosetundra",
    "PrK": "3",
    "PrK-tekst": "Preget av miljøstress",
    "GrL": "S ",
    "Definisjonsgrunnlag-tekst": "miljøstressbetinget",
    "NiN[1] ": "T16",
    "dLKM": "NG,PF,IO",
    "hLKM": "",
    "tLKM": "KA ",
    "uLKM": "VM",
    "Kunnskapsgrunnlag - Hovedtypen generelt": "2"
  },
  {
    "Kunnskapsgrunnlag - Grunntypeinndelingen": "1",
    "HTK": "T10",
    "Navn": "Arktisk steppe",
    "PrK": "3",
    "PrK-tekst": "Preget av miljøstress",
    "GrL": "S",
    "Definisjonsgrunnlag-tekst": "miljøstressbetinget",
    "NiN[1] ": "T27 [2-3]",
    "dLKM": "AS",
    "hLKM": "",
    "tLKM": "VI",
    "uLKM": "",
    "Kunnskapsgrunnlag - Hovedtypen generelt": "2"
  },
  {
    "Kunnskapsgrunnlag - Grunntypeinndelingen": "2",
    "HTK": "T11",
    "Navn": "Saltanrikingsmark i fjæresonen",
    "PrK": "3",
    "PrK-tekst": "Preget av miljøstress",
    "GrL": "S ",
    "Definisjonsgrunnlag-tekst": "miljøstressbetinget",
    "NiN[1] ": "S7 [13, 7-8pp]",
    "dLKM": "TV,SF",
    "hLKM": "",
    "tLKM": "TV,S1",
    "uLKM": "",
    "Kunnskapsgrunnlag - Hovedtypen generelt": "3"
  },
  {
    "Kunnskapsgrunnlag - Grunntypeinndelingen": "3",
    "HTK": "T12",
    "Navn": "Strandeng",
    "PrK": "3",
    "PrK-tekst": "Preget av miljøstress",
    "GrL": "S ",
    "Definisjonsgrunnlag-tekst": "miljøstressbetinget",
    "NiN[1] ": "S7 [1-8] p.p.",
    "dLKM": "TV,SA",
    "hLKM": "TV ",
    "tLKM": "",
    "uLKM": "SA,HI,S1,VM,KA",
    "Kunnskapsgrunnlag - Hovedtypen generelt": "3"
  },
  {
    "Kunnskapsgrunnlag - Grunntypeinndelingen": "2",
    "HTK": "T13",
    "Navn": "Rasmark",
    "PrK": "4",
    "PrK-tekst": "Preget av aktiv regulerende forstyrrelse ",
    "GrL": "RL",
    "Definisjonsgrunnlag-tekst": "betinget av regulerende forstyrrelse, ikke jorddekt",
    "NiN[1] ": "T17 [1-4]",
    "dLKM": "RU ",
    "hLKM": "KA,S1 ",
    "tLKM": "UE,RU ",
    "uLKM": "BK,VI",
    "Kunnskapsgrunnlag - Hovedtypen generelt": "3"
  },
  {
    "Kunnskapsgrunnlag - Grunntypeinndelingen": "4",
    "HTK": "T14",
    "Navn": "Rabbe",
    "PrK": "4",
    "PrK-tekst": "Preget av aktiv regulerende forstyrrelse ",
    "GrL": "R",
    "Definisjonsgrunnlag-tekst": "betinget av regulerende forstyrrelse",
    "NiN[1] ": "T27 [1] T29 [23-25]",
    "dLKM": "VI",
    "hLKM": "",
    "tLKM": "VI,KA",
    "uLKM": "",
    "Kunnskapsgrunnlag - Hovedtypen generelt": "4"
  },
  {
    "Kunnskapsgrunnlag - Grunntypeinndelingen": "2",
    "HTK": "T15",
    "Navn": "Fosse-eng",
    "PrK": "4",
    "PrK-tekst": "Preget av aktiv regulerende forstyrrelse ",
    "GrL": "R",
    "Definisjonsgrunnlag-tekst": "betinget av regulerende forstyrrelse",
    "NiN[1] ": "T10",
    "dLKM": "VS",
    "hLKM": "",
    "tLKM": "KA ",
    "uLKM": "VS,HI,KI",
    "Kunnskapsgrunnlag - Hovedtypen generelt": "2"
  },
  {
    "Kunnskapsgrunnlag - Grunntypeinndelingen": "3",
    "HTK": "T16",
    "Navn": "Rasmarkhei og -eng",
    "PrK": "4",
    "PrK-tekst": "Preget av aktiv regulerende forstyrrelse ",
    "GrL": "R",
    "Definisjonsgrunnlag-tekst": "betinget av regulerende forstyrrelse",
    "NiN[1] ": "T17 [5-14]",
    "dLKM": "RU",
    "hLKM": "KA ",
    "tLKM": "RU,KI ",
    "uLKM": "UF,HI,BK,VI,VM",
    "Kunnskapsgrunnlag - Hovedtypen generelt": "3"
  },
  {
    "Kunnskapsgrunnlag - Grunntypeinndelingen": "3",
    "HTK": "T17",
    "Navn": "Aktiv skredmark",
    "PrK": "5",
    "PrK-tekst": "Preget av aktiv destabiliserende forstyrrelse",
    "GrL": "DL",
    "Definisjonsgrunnlag-tekst": "betinget av destabiliserende forstyrrelse, ikke jorddekt",
    "NiN[1] ": "T18 [1-3]",
    "dLKM": "SU",
    "hLKM": "S1 ",
    "tLKM": "",
    "uLKM": "SU,KA,KI",
    "Kunnskapsgrunnlag - Hovedtypen generelt": "2"
  },
  {
    "Kunnskapsgrunnlag - Grunntypeinndelingen": "2",
    "HTK": "T18",
    "Navn": "Åpen flomfastmark",
    "PrK": "5",
    "PrK-tekst": "Preget av aktiv destabiliserende forstyrrelse",
    "GrL": "DL",
    "Definisjonsgrunnlag-tekst": "betinget av destabiliserende forstyrrelse, ikke jorddekt",
    "NiN[1] ": "T8",
    "dLKM": "VF",
    "hLKM": "S1 ",
    "tLKM": "VF,KA,ER ",
    "uLKM": "IF,KI,HI",
    "Kunnskapsgrunnlag - Hovedtypen generelt": "2"
  },
  {
    "Kunnskapsgrunnlag - Grunntypeinndelingen": "2",
    "HTK": "T19",
    "Navn": "Oppfrysingsmark",
    "PrK": "5",
    "PrK-tekst": "Preget av aktiv destabiliserende forstyrrelse",
    "GrL": "D",
    "Definisjonsgrunnlag-tekst": "betinget av destabiliserende forstyrrelse",
    "NiN[1] ": "T28 pp.",
    "dLKM": "PF,OF",
    "hLKM": "",
    "tLKM": "KA",
    "uLKM": "",
    "Kunnskapsgrunnlag - Hovedtypen generelt": "2"
  },
  {
    "Kunnskapsgrunnlag - Grunntypeinndelingen": "3",
    "HTK": "T20",
    "Navn": "Isinnfrysingsmark",
    "PrK": "5",
    "PrK-tekst": "Preget av aktiv destabiliserende forstyrrelse",
    "GrL": "D",
    "Definisjonsgrunnlag-tekst": "betinget av destabiliserende forstyrrelse",
    "NiN[1] ": "T24",
    "dLKM": "IF",
    "hLKM": "",
    "tLKM": "KA",
    "uLKM": "",
    "Kunnskapsgrunnlag - Hovedtypen generelt": "3"
  },
  {
    "Kunnskapsgrunnlag - Grunntypeinndelingen": "3",
    "HTK": "T21",
    "Navn": "Sanddynemark",
    "PrK": "5",
    "PrK-tekst": "Preget av aktiv destabiliserende forstyrrelse",
    "GrL": "D",
    "Definisjonsgrunnlag-tekst": "betinget av destabiliserende forstyrrelse",
    "NiN[1] ": "T13, S6[1,2]",
    "dLKM": "SS",
    "hLKM": "SS ",
    "tLKM": "VI,VM ",
    "uLKM": "HI",
    "Kunnskapsgrunnlag - Hovedtypen generelt": "4"
  },
  {
    "Kunnskapsgrunnlag - Grunntypeinndelingen": "3",
    "HTK": "T22",
    "Navn": "Fjellgrashei og grastundra",
    "PrK": "5",
    "PrK-tekst": "Preget av aktiv destabiliserende forstyrrelse",
    "GrL": "D",
    "Definisjonsgrunnlag-tekst": "betinget av destabiliserende forstyrrelse",
    "NiN[1] ": "T28 pp, T29 [17-22]",
    "dLKM": "JF",
    "hLKM": "",
    "tLKM": "KA,SV ",
    "uLKM": "VM",
    "Kunnskapsgrunnlag - Hovedtypen generelt": "3"
  },
  {
    "Kunnskapsgrunnlag - Grunntypeinndelingen": "2",
    "HTK": "T23",
    "Navn": "Ferskvanns-driftvoll",
    "PrK": "5",
    "PrK-tekst": "Preget av aktiv destabiliserende forstyrrelse",
    "GrL": "D",
    "Definisjonsgrunnlag-tekst": "betinget av destabiliserende forstyrrelse",
    "NiN[1] ": "-",
    "dLKM": "TV,IO",
    "hLKM": "",
    "tLKM": "",
    "uLKM": "",
    "Kunnskapsgrunnlag - Hovedtypen generelt": "1"
  },
  {
    "Kunnskapsgrunnlag - Grunntypeinndelingen": "2",
    "HTK": "T24",
    "Navn": "Driftvoll",
    "PrK": "5",
    "PrK-tekst": "Preget av aktiv destabiliserende forstyrrelse",
    "GrL": "D",
    "Definisjonsgrunnlag-tekst": "betinget av destabiliserende forstyrrelse",
    "NiN[1] ": "S3",
    "dLKM": "TV,IO,SA",
    "hLKM": "VF ",
    "tLKM": "",
    "uLKM": "VM",
    "Kunnskapsgrunnlag - Hovedtypen generelt": "3"
  },
  {
    "Kunnskapsgrunnlag - Grunntypeinndelingen": "1",
    "HTK": "T25",
    "Navn": "Historisk skredmark",
    "PrK": "6a",
    "PrK-tekst": "Preget av historisk disruptivt miljøstress eller destabiliserende forstyrrelse - Rask suksesjon",
    "GrL": "XD",
    "Definisjonsgrunnlag-tekst": "betinget av destabiliserende historisk forstyrrelse",
    "NiN[1] ": "T18 p.p.",
    "dLKM": "SH",
    "hLKM": "S1 ",
    "tLKM": "",
    "uLKM": "KA,KI",
    "Kunnskapsgrunnlag - Hovedtypen generelt": "1"
  },
  {
    "Kunnskapsgrunnlag - Grunntypeinndelingen": "2",
    "HTK": "T26",
    "Navn": "Breforland og snøavsmeltingsområde",
    "PrK": "6b",
    "PrK-tekst": "Preget av historisk disruptivt miljøstress eller destabiliserende forstyrrelse - Langsom eller frosset suksesjon ",
    "GrL": "XSL ",
    "Definisjonsgrunnlag-tekst": "betinget av historisk miljøstress, ikke jorddekt",
    "NiN[1] ": "T11",
    "dLKM": "SH",
    "hLKM": "",
    "tLKM": "SV,VM,LA,S1 ",
    "uLKM": "KA,KI ",
    "Kunnskapsgrunnlag - Hovedtypen generelt": "4"
  },
  {
    "Kunnskapsgrunnlag - Grunntypeinndelingen": "1",
    "HTK": "T27",
    "Navn": "Blokkmark",
    "PrK": "6b",
    "PrK-tekst": "Preget av historisk disruptivt miljøstress eller destabiliserende forstyrrelse - Langsom eller frosset suksesjon ",
    "GrL": "XRL",
    "Definisjonsgrunnlag-tekst": "betinget av historisk regulerende forstyrrelse, ikke jorddekt",
    "NiN[1] ": "T22",
    "dLKM": "SH",
    "hLKM": "SV ",
    "tLKM": "KA,VI,LA ",
    "uLKM": "BK,S1,UE",
    "Kunnskapsgrunnlag - Hovedtypen generelt": "1"
  },
  {
    "Kunnskapsgrunnlag - Grunntypeinndelingen": "3",
    "HTK": "T28",
    "Navn": "Polarørken",
    "PrK": "6b",
    "PrK-tekst": "Preget av historisk disruptivt miljøstress eller destabiliserende forstyrrelse - Langsom eller frosset suksesjon ",
    "GrL": "XRL",
    "Definisjonsgrunnlag-tekst": "betinget av historisk regulerende forstyrrelse, ikke jorddekt",
    "NiN[1] ": "T21",
    "dLKM": "SH,PF",
    "hLKM": "KA",
    "tLKM": "",
    "uLKM": "",
    "Kunnskapsgrunnlag - Hovedtypen generelt": "2"
  },
  {
    "Kunnskapsgrunnlag - Grunntypeinndelingen": "3",
    "HTK": "T29",
    "Navn": "Grus- og steindominert strand og strandlinje",
    "PrK": "6b",
    "PrK-tekst": "Preget av historisk disruptivt miljøstress eller destabiliserende forstyrrelse - Langsom eller frosset suksesjon ",
    "GrL": "XRL",
    "Definisjonsgrunnlag-tekst": "betinget av historisk regulerende forstyrrelse, ikke jorddekt",
    "NiN[1] ": "T12",
    "dLKM": "SH",
    "hLKM": "",
    "tLKM": "S1,LA,VI,TV ",
    "uLKM": "HI",
    "Kunnskapsgrunnlag - Hovedtypen generelt": "3"
  },
  {
    "Kunnskapsgrunnlag - Grunntypeinndelingen": "3",
    "HTK": "T30",
    "Navn": "Flomskogsmark",
    "PrK": "9",
    "PrK-tekst": "Preget av aktiv destabiliserende forstyrrelse",
    "GrL": "AD",
    "Definisjonsgrunnlag-tekst": "betinget av destabiliserende forstyrrelse, strukturerende artsgruppe",
    "NiN[1] ": "T7",
    "dLKM": "VF",
    "hLKM": "",
    "tLKM": "S1,VF,KI,ER",
    "uLKM": "KA,HI,SA",
    "Kunnskapsgrunnlag - Hovedtypen generelt": "2"
  },
  {
    "Kunnskapsgrunnlag - Grunntypeinndelingen": "4",
    "HTK": "T31",
    "Navn": "Boreal hei",
    "PrK": "10",
    "PrK-tekst": "Semi-naturlig system uten eller med svake spor av hevd",
    "GrL": "M",
    "Definisjonsgrunnlag-tekst": "semi-naturlig mark uten hevdpreg",
    "NiN[1] ": "T26",
    "dLKM": "MX",
    "hLKM": "KA,UF ",
    "tLKM": "KI ",
    "uLKM": "BK,HI,VM",
    "Kunnskapsgrunnlag - Hovedtypen generelt": "2"
  },
  {
    "Kunnskapsgrunnlag - Grunntypeinndelingen": "4",
    "HTK": "T32",
    "Navn": "Semi-naturlig eng",
    "PrK": "11b",
    "PrK-tekst": "Semi-naturlig hevdpreget system ",
    "GrL": "MHJ",
    "Definisjonsgrunnlag-tekst": "semi-naturlig jordbruksmark",
    "NiN[1] ": "T4",
    "dLKM": "HI ",
    "hLKM": "KA,HI ",
    "tLKM": "KI,UF,SS ",
    "uLKM": "SP,VM",
    "Kunnskapsgrunnlag - Hovedtypen generelt": "4"
  },
  {
    "Kunnskapsgrunnlag - Grunntypeinndelingen": "2",
    "HTK": "T33",
    "Navn": "Semi-naturlig strandeng",
    "PrK": "11b",
    "PrK-tekst": "Semi-naturlig hevdpreget system ",
    "GrL": "MHJ ",
    "Definisjonsgrunnlag-tekst": "semi-naturlig jordbruksmark",
    "NiN[1] ": "S7 [1-6] p.p.",
    "dLKM": "HI,TV,SA",
    "hLKM": "",
    "tLKM": "TV ",
    "uLKM": "SA,SP,VM,S1,HI,KA",
    "Kunnskapsgrunnlag - Hovedtypen generelt": "3"
  },
  {
    "Kunnskapsgrunnlag - Grunntypeinndelingen": "4",
    "HTK": "T34",
    "Navn": "Kystlynghei",
    "PrK": "11b",
    "PrK-tekst": "Semi-naturlig hevdpreget system ",
    "GrL": "MHJ",
    "Definisjonsgrunnlag-tekst": "semi-naturlig jordbruksmark",
    "NiN[1] ": "T5",
    "dLKM": "HI,HR",
    "hLKM": "KA,UF ",
    "tLKM": "VM ",
    "uLKM": "BK",
    "Kunnskapsgrunnlag - Hovedtypen generelt": "4"
  },
  {
    "Kunnskapsgrunnlag - Grunntypeinndelingen": "3",
    "HTK": "T35",
    "Navn": "Sterkt endret åpen fastmark med løsmassedekke",
    "PrK": "12a",
    "PrK-tekst": "Sterkt endret system uten eller med svake spor etter av hevd - Rask suksesjon",
    "GrL": "N",
    "Definisjonsgrunnlag-tekst": "sterk menneskebetinget forstyrrelse",
    "NiN[1] ": "T2 pp.",
    "dLKM": "SX",
    "hLKM": "",
    "tLKM": "S1 ",
    "uLKM": "KA",
    "Kunnskapsgrunnlag - Hovedtypen generelt": "2"
  },
  {
    "Kunnskapsgrunnlag - Grunntypeinndelingen": "2",
    "HTK": "T36",
    "Navn": "Ny fastmark på tidligere våtmark og ferskvannsbunn",
    "PrK": "12a",
    "PrK-tekst": "Sterkt endret system uten eller med svake spor etter av hevd - Rask suksesjon",
    "GrL": "N",
    "Definisjonsgrunnlag-tekst": "sterk menneskebetinget forstyrrelse",
    "NiN[1] ": "T2 pp.",
    "dLKM": "SX",
    "hLKM": "HS",
    "tLKM": "",
    "uLKM": "KA",
    "Kunnskapsgrunnlag - Hovedtypen generelt": "2"
  },
  {
    "Kunnskapsgrunnlag - Grunntypeinndelingen": "3",
    "HTK": "T37",
    "Navn": "Ny fastmark på sterkt modifi-serte og syntetiske substrater, i rask suksesjon",
    "PrK": "12a",
    "PrK-tekst": "Sterkt endret system uten eller med svake spor etter av hevd - Rask suksesjon",
    "GrL": "N",
    "Definisjonsgrunnlag-tekst": "sterk menneskebetinget forstyrrelse",
    "NiN[1] ": "T2 pp.",
    "dLKM": "SX",
    "hLKM": "",
    "tLKM": "HS",
    "uLKM": "",
    "Kunnskapsgrunnlag - Hovedtypen generelt": "2"
  },
  {
    "Kunnskapsgrunnlag - Grunntypeinndelingen": "2",
    "HTK": "T38",
    "Navn": "Treplantasje",
    "PrK": "12a",
    "PrK-tekst": "Sterkt endret system uten eller med svake spor etter av hevd - Rask suksesjon",
    "GrL": "N",
    "Definisjonsgrunnlag-tekst": "sterk menneskebetinget forstyrrelse",
    "NiN[1] ": "T23 pp.",
    "dLKM": "SX",
    "hLKM": "",
    "tLKM": "",
    "uLKM": "UF,KA",
    "Kunnskapsgrunnlag - Hovedtypen generelt": "4"
  },
  {
    "Kunnskapsgrunnlag - Grunntypeinndelingen": "2",
    "HTK": "T39",
    "Navn": "Sterkt endret eller ny fastmark i langsom suksesjon",
    "PrK": "12b",
    "PrK-tekst": "Sterkt endret system uten eller med svake spor etter av hevd - Langsom suksesjon",
    "GrL": "NL",
    "Definisjonsgrunnlag-tekst": "sterk menneskebetinget forstyrrelse, i langsom suksesjon",
    "NiN[1] ": "T2 pp.",
    "dLKM": "SX",
    "hLKM": "",
    "tLKM": "HS,LA",
    "uLKM": "",
    "Kunnskapsgrunnlag - Hovedtypen generelt": "2"
  },
  {
    "Kunnskapsgrunnlag - Grunntypeinndelingen": "1",
    "HTK": "T40",
    "Navn": "Sterkt endret fastmark med preg av semi-naturlig eng",
    "PrK": "13a",
    "PrK-tekst": "Sterkt endret system uten jordbruksproduksjon som hovedformål",
    "GrL": "NH",
    "Definisjonsgrunnlag-tekst": "sterk menneskebetinget forstyrrelse, med hevdpreg",
    "NiN[1] ": "T2 pp.",
    "dLKM": "SX,MB ",
    "hLKM": "",
    "tLKM": "",
    "uLKM": "KA,UF,SP,VM,SS,SA",
    "Kunnskapsgrunnlag - Hovedtypen generelt": "1"
  },
  {
    "Kunnskapsgrunnlag - Grunntypeinndelingen": "2",
    "HTK": "T41",
    "Navn": "Oppdyrket mark med preg av semi-naturlig eng",
    "PrK": "13b",
    "PrK-tekst": "Sterkt endret system preget av ekstensiv hevd - Oppdyrka mark",
    "GrL": "NHJ",
    "Definisjonsgrunnlag-tekst": "sterkt endret jordbruksmark",
    "NiN[1] ": "T3 pp.",
    "dLKM": "SX,MB ",
    "hLKM": "",
    "tLKM": "",
    "uLKM": "KA,HI,SP,VM",
    "Kunnskapsgrunnlag - Hovedtypen generelt": "2"
  },
  {
    "Kunnskapsgrunnlag - Grunntypeinndelingen": "1",
    "HTK": "T42",
    "Navn": "Sterkt endret, hyppig bearbeidet fastmark med intensivt hevdpreg",
    "PrK": "14a",
    "PrK-tekst": "Sterkt endret system uten jordbruksproduksjon som hovedformål",
    "GrL": "NH",
    "Definisjonsgrunnlag-tekst": "sterk menneskebetinget forstyrrelse, med hevdpreg",
    "NiN[1] ": "T2 pp.",
    "dLKM": "SX,MB ",
    "hLKM": "",
    "tLKM": "",
    "uLKM": "",
    "Kunnskapsgrunnlag - Hovedtypen generelt": "1"
  },
  {
    "Kunnskapsgrunnlag - Grunntypeinndelingen": "1",
    "HTK": "T43",
    "Navn": "Sterkt endret, varig fastmark med intensivt hevdpreg",
    "PrK": "14a",
    "PrK-tekst": "Sterkt endret system uten jordbruksproduksjon som hovedformål",
    "GrL": "NH",
    "Definisjonsgrunnlag-tekst": "sterk menneskebetinget forstyrrelse, med hevdpreg",
    "NiN[1] ": "T2 pp.",
    "dLKM": "SX,MB ",
    "hLKM": "",
    "tLKM": "",
    "uLKM": "KA,HI,VM ",
    "Kunnskapsgrunnlag - Hovedtypen generelt": "1"
  },
  {
    "Kunnskapsgrunnlag - Grunntypeinndelingen": "2",
    "HTK": "T44",
    "Navn": "Åker",
    "PrK": "14b",
    "PrK-tekst": "Sterkt endret hevdpreget system - Oppdyrka mark",
    "GrL": "NHJ",
    "Definisjonsgrunnlag-tekst": "sterkt endret jordbruksmark",
    "NiN[1] ": "T3 pp.",
    "dLKM": "SX,MB ",
    "hLKM": "",
    "tLKM": "",
    "uLKM": "KA,S1,VM",
    "Kunnskapsgrunnlag - Hovedtypen generelt": "2"
  },
  {
    "Kunnskapsgrunnlag - Grunntypeinndelingen": "2",
    "HTK": "T45",
    "Navn": "Oppdyrket varig eng",
    "PrK": "14b",
    "PrK-tekst": "Sterkt endret hevdpreget system - Oppdyrka mark",
    "GrL": "NHJ",
    "Definisjonsgrunnlag-tekst": "sterkt endret jordbruksmark",
    "NiN[1] ": "T3 pp.",
    "dLKM": "SX,MB ",
    "hLKM": "HI ",
    "tLKM": "SP ",
    "uLKM": "KA,S1,VM",
    "Kunnskapsgrunnlag - Hovedtypen generelt": "2"
  },
  {
    "Kunnskapsgrunnlag - Grunntypeinndelingen": "3",
    "HTK": "V1",
    "Navn": "Åpen jordvannsmyr",
    "PrK": "1",
    "PrK-tekst": "Uten variasjon i artssammensetning betinget av strukturerende artsgruppe",
    "GrL": "0",
    "Definisjonsgrunnlag-tekst": "normal hovedtype",
    "NiN[1] ": "V6[4-15], V7 [2-7] p.p.",
    "dLKM": "",
    "hLKM": "KA,TV ",
    "tLKM": "MF,KI,SA ",
    "uLKM": "VT,TE",
    "Kunnskapsgrunnlag - Hovedtypen generelt": "3"
  },
  {
    "Kunnskapsgrunnlag - Grunntypeinndelingen": "4",
    "HTK": "V2",
    "Navn": "Myr- og sumpskogsmark",
    "PrK": "2",
    "PrK-tekst": "Med variasjon i artssammensetning betinget av strukturerende artsgruppe",
    "GrL": "A",
    "Definisjonsgrunnlag-tekst": "normal, strukturerende artsgruppe",
    "NiN[1] ": "V7 [2-7] p.p.",
    "dLKM": "",
    "hLKM": "KA ",
    "tLKM": "TV,KI ",
    "uLKM": "",
    "Kunnskapsgrunnlag - Hovedtypen generelt": "3"
  },
  {
    "Kunnskapsgrunnlag - Grunntypeinndelingen": "4",
    "HTK": "V3",
    "Navn": "Nedbørsmyr ",
    "PrK": "3",
    "PrK-tekst": "Preget av miljøstress",
    "GrL": "S",
    "Definisjonsgrunnlag-tekst": "miljøstressbetinget",
    "NiN[1] ": "V6[1-3]",
    "dLKM": "VT",
    "hLKM": "TV ",
    "tLKM": "MF,VI ",
    "uLKM": "TE",
    "Kunnskapsgrunnlag - Hovedtypen generelt": "4"
  },
  {
    "Kunnskapsgrunnlag - Grunntypeinndelingen": "4",
    "HTK": "V4",
    "Navn": "Kaldkilde",
    "PrK": "3",
    "PrK-tekst": "Preget av miljøstress",
    "GrL": "S ",
    "Definisjonsgrunnlag-tekst": "miljøstressbetinget",
    "NiN[1] ": "V3, V4",
    "dLKM": "KI",
    "hLKM": "KA ",
    "tLKM": "KI,KT",
    "uLKM": "HI",
    "Kunnskapsgrunnlag - Hovedtypen generelt": "2"
  },
  {
    "Kunnskapsgrunnlag - Grunntypeinndelingen": "1",
    "HTK": "V5",
    "Navn": "Varm kilde",
    "PrK": "3",
    "PrK-tekst": "Preget av miljøstress",
    "GrL": "S ",
    "Definisjonsgrunnlag-tekst": "miljøstressbetinget",
    "NiN[1] ": "V5",
    "dLKM": "KI,JV",
    "hLKM": "",
    "tLKM": "JV",
    "uLKM": "JV",
    "Kunnskapsgrunnlag - Hovedtypen generelt": "1"
  },
  {
    "Kunnskapsgrunnlag - Grunntypeinndelingen": "3",
    "HTK": "V6",
    "Navn": "Våtsnøleie og snøleiekilde",
    "PrK": "3",
    "PrK-tekst": "Preget av miljøstress",
    "GrL": "S",
    "Definisjonsgrunnlag-tekst": "miljøstressbetinget",
    "NiN[1] ": "V9, T30 p.p.",
    "dLKM": "SV,IO",
    "hLKM": "SV ",
    "tLKM": "KA,KI",
    "uLKM": "",
    "Kunnskapsgrunnlag - Hovedtypen generelt": "2"
  },
  {
    "Kunnskapsgrunnlag - Grunntypeinndelingen": "3",
    "HTK": "V7",
    "Navn": "Arktisk permafrost-våtmark",
    "PrK": "3",
    "PrK-tekst": "Preget av miljøstress",
    "GrL": "S",
    "Definisjonsgrunnlag-tekst": "miljøstressbetinget",
    "NiN[1] ": "V8",
    "dLKM": "PF",
    "hLKM": "",
    "tLKM": "KA ",
    "uLKM": "TV",
    "Kunnskapsgrunnlag - Hovedtypen generelt": "3"
  },
  {
    "Kunnskapsgrunnlag - Grunntypeinndelingen": "4",
    "HTK": "V8",
    "Navn": "Strandsumpskogsmark",
    "PrK": "7",
    "PrK-tekst": "Preget av miljøstress med strukturerende artsgruppe",
    "GrL": "AS",
    "Definisjonsgrunnlag-tekst": "miljøstressbetinget, strukturerende artsgruppe",
    "NiN[1] ": "V7 p.p.",
    "dLKM": "VT",
    "hLKM": "",
    "tLKM": "KA,SA",
    "uLKM": "",
    "Kunnskapsgrunnlag - Hovedtypen generelt": "2"
  },
  {
    "Kunnskapsgrunnlag - Grunntypeinndelingen": "1",
    "HTK": "V9",
    "Navn": "Semi-naturlig myr ",
    "PrK": "11b",
    "PrK-tekst": "Semi-naturlig hevdpreget system ",
    "GrL": "MHJ",
    "Definisjonsgrunnlag-tekst": "semi-naturlig jordbruksmark",
    "NiN[1] ": "V6, V7 p.p.",
    "dLKM": "HI",
    "hLKM": "KA ",
    "tLKM": "",
    "uLKM": "TV,KI,SP",
    "Kunnskapsgrunnlag - Hovedtypen generelt": "3"
  },
  {
    "Kunnskapsgrunnlag - Grunntypeinndelingen": "2",
    "HTK": "V10",
    "Navn": "Semi-naturlig våteng",
    "PrK": "11b",
    "PrK-tekst": "Semi-naturlig hevdpreget system ",
    "GrL": "MHJ",
    "Definisjonsgrunnlag-tekst": "semi-naturlig jordbruksmark",
    "NiN[1] ": "T4 [9]",
    "dLKM": "HI,IO",
    "hLKM": "",
    "tLKM": "KA,KI",
    "uLKM": "SP",
    "Kunnskapsgrunnlag - Hovedtypen generelt": "2"
  },
  {
    "Kunnskapsgrunnlag - Grunntypeinndelingen": "1",
    "HTK": "V11",
    "Navn": "Torvtak",
    "PrK": "12a",
    "PrK-tekst": "Sterkt endret system uten eller med svake spor etter av hevd - Rask suksesjon",
    "GrL": "N",
    "Definisjonsgrunnlag-tekst": "sterk menneskebetinget forstyrrelse",
    "NiN[1] ": "V1[3]",
    "dLKM": "SX",
    "hLKM": "",
    "tLKM": "KA",
    "uLKM": "",
    "Kunnskapsgrunnlag - Hovedtypen generelt": "2"
  },
  {
    "Kunnskapsgrunnlag - Grunntypeinndelingen": "2",
    "HTK": "V12",
    "Navn": "Grøftet torvmark",
    "PrK": "12a",
    "PrK-tekst": "Sterkt endret system uten eller med svake spor etter av hevd - Rask suksesjon",
    "GrL": "N",
    "Definisjonsgrunnlag-tekst": "sterk menneskebetinget forstyrrelse",
    "NiN[1] ": "V1[1,2]",
    "dLKM": "",
    "hLKM": "",
    "tLKM": "",
    "uLKM": "VT,KA",
    "Kunnskapsgrunnlag - Hovedtypen generelt": "3"
  },
  {
    "Kunnskapsgrunnlag - Grunntypeinndelingen": "1",
    "HTK": "V13",
    "Navn": "Ny våtmark",
    "PrK": "12a",
    "PrK-tekst": "Sterkt endret system uten eller med svake spor etter av hevd - Rask suksesjon",
    "GrL": "N",
    "Definisjonsgrunnlag-tekst": "sterk menneskebetinget forstyrrelse",
    "NiN[1] ": "V2",
    "dLKM": "SX",
    "hLKM": "",
    "tLKM": "HS,IO ",
    "uLKM": "KA",
    "Kunnskapsgrunnlag - Hovedtypen generelt": "1"
  },
  {
    "Kunnskapsgrunnlag - Grunntypeinndelingen": "2",
    "HTK": "H1",
    "Navn": "Havvannmasser",
    "PrK": "1",
    "PrK-tekst": "Uten variasjon i artssammensetning betinget av strukturerende artsgruppe",
    "GrL": "0",
    "Definisjonsgrunnlag-tekst": "normal hovedtype",
    "NiN[1] ": "-",
    "dLKM": "",
    "hLKM": "DM ",
    "tLKM": "KY ",
    "uLKM": "JV",
    "Kunnskapsgrunnlag - Hovedtypen generelt": "3"
  },
  {
    "Kunnskapsgrunnlag - Grunntypeinndelingen": "2",
    "HTK": "H2",
    "Navn": "Sirkulerende vannmasser i fysisk avgrensete saltvannsforekomster ",
    "PrK": "3",
    "PrK-tekst": "Preget av miljøstress",
    "GrL": "S ",
    "Definisjonsgrunnlag-tekst": "miljøstressbetinget",
    "NiN[1] ": "-",
    "dLKM": "SM",
    "hLKM": "SM ",
    "tLKM": "SA ",
    "uLKM": "",
    "Kunnskapsgrunnlag - Hovedtypen generelt": "2"
  },
  {
    "Kunnskapsgrunnlag - Grunntypeinndelingen": "2",
    "HTK": "H3",
    "Navn": "Ikke-sirkulerende marine vannmasser i fysisk avgrensete saltvannsforekomster",
    "PrK": "3",
    "PrK-tekst": "Preget av miljøstress",
    "GrL": "S",
    "Definisjonsgrunnlag-tekst": "miljøstressbetinget",
    "NiN[1] ": "-",
    "dLKM": "OM",
    "hLKM": "",
    "tLKM": "",
    "uLKM": "",
    "Kunnskapsgrunnlag - Hovedtypen generelt": "1"
  },
  {
    "Kunnskapsgrunnlag - Grunntypeinndelingen": "1",
    "HTK": "H4",
    "Navn": "Sterkt endrete marine vannmasser",
    "PrK": "12a",
    "PrK-tekst": "Sterkt endret system uten eller med svake spor etter av hevd - Rask suksesjon",
    "GrL": "N",
    "Definisjonsgrunnlag-tekst": "sterk menneskebetinget forstyrrelse",
    "NiN[1] ": "-",
    "dLKM": "SY",
    "hLKM": "",
    "tLKM": "SY ",
    "uLKM": "SM,SA",
    "Kunnskapsgrunnlag - Hovedtypen generelt": "2"
  },
  {
    "Kunnskapsgrunnlag - Grunntypeinndelingen": "2",
    "HTK": "F1",
    "Navn": "Elvevannmasser",
    "PrK": "1",
    "PrK-tekst": "Uten variasjon i artssammensetning betinget av strukturerende artsgruppe",
    "GrL": "0",
    "Definisjonsgrunnlag-tekst": "normal hovedtype",
    "NiN[1] ": "-",
    "dLKM": "",
    "hLKM": "",
    "tLKM": "VF,HU,KA ",
    "uLKM": "TU",
    "Kunnskapsgrunnlag - Hovedtypen generelt": "3"
  },
  {
    "Kunnskapsgrunnlag - Grunntypeinndelingen": "2",
    "HTK": "F2",
    "Navn": "Sirkulerende innsjø-vannmasser",
    "PrK": "1",
    "PrK-tekst": "Uten variasjon i artssammensetning betinget av strukturerende artsgruppe",
    "GrL": "0",
    "Definisjonsgrunnlag-tekst": "normal hovedtype",
    "NiN[1] ": "-",
    "dLKM": "",
    "hLKM": "SM ",
    "tLKM": "KA,HU,TU ",
    "uLKM": "KO",
    "Kunnskapsgrunnlag - Hovedtypen generelt": "3"
  },
  {
    "Kunnskapsgrunnlag - Grunntypeinndelingen": "2",
    "HTK": "F3",
    "Navn": "Ikke-sirkulerende innsjø-vannmasser",
    "PrK": "3",
    "PrK-tekst": "Preget av miljøstress",
    "GrL": "S ",
    "Definisjonsgrunnlag-tekst": "miljøstressbetinget",
    "NiN[1] ": "-",
    "dLKM": "OM",
    "hLKM": "",
    "tLKM": "",
    "uLKM": "FK",
    "Kunnskapsgrunnlag - Hovedtypen generelt": "1"
  },
  {
    "Kunnskapsgrunnlag - Grunntypeinndelingen": "1",
    "HTK": "F4",
    "Navn": "Sterkt endrete elvevannmasser",
    "PrK": "12a",
    "PrK-tekst": "Sterkt endret system uten eller med svake spor etter av hevd - Rask suksesjon",
    "GrL": "N",
    "Definisjonsgrunnlag-tekst": "sterk menneskebetinget forstyrrelse",
    "NiN[1] ": "-",
    "dLKM": "SY",
    "hLKM": "",
    "tLKM": "SY ",
    "uLKM": "VF,HU,KA,TU",
    "Kunnskapsgrunnlag - Hovedtypen generelt": "2"
  },
  {
    "Kunnskapsgrunnlag - Grunntypeinndelingen": "1",
    "HTK": "F5",
    "Navn": "Sterkt endrete innsjøvannmasser",
    "PrK": "12a",
    "PrK-tekst": "Sterkt endret system uten eller med svake spor etter av hevd - Rask suksesjon",
    "GrL": "N",
    "Definisjonsgrunnlag-tekst": "sterk menneskebetinget forstyrrelse",
    "NiN[1] ": "-",
    "dLKM": "SY",
    "hLKM": "",
    "tLKM": "SY ",
    "uLKM": "SM,KA,HU,TU,KO",
    "Kunnskapsgrunnlag - Hovedtypen generelt": "2"
  },
  {
    "Kunnskapsgrunnlag - Grunntypeinndelingen": "1",
    "HTK": "I1",
    "Navn": "Snø- og isdekt fastmark",
    "PrK": "1",
    "PrK-tekst": "Uten variasjon i artssammensetning betinget av strukturerende artsgruppe",
    "GrL": "0",
    "Definisjonsgrunnlag-tekst": "normal hovedtype",
    "NiN[1] ": "T1",
    "dLKM": "",
    "hLKM": "",
    "tLKM": "",
    "uLKM": "",
    "Kunnskapsgrunnlag - Hovedtypen generelt": "1"
  },
  {
    "Kunnskapsgrunnlag - Grunntypeinndelingen": "1",
    "HTK": "I2",
    "Navn": "Polar havis",
    "PrK": "1",
    "PrK-tekst": "Uten variasjon i artssammensetning betinget av strukturerende artsgruppe",
    "GrL": "0",
    "Definisjonsgrunnlag-tekst": "normal hovedtype",
    "NiN[1] ": "-",
    "dLKM": "",
    "hLKM": "",
    "tLKM": "",
    "uLKM": "",
    "Kunnskapsgrunnlag - Hovedtypen generelt": "3"
  }
]
